Metadata-Version: 2.4
Name: microservice_chassis_grupo2_cc
Version: 0.1.4
Summary: A reusable library for microservices
Home-page: https://github.com/Grupo-MACC/Chassis
Author: Grupo 2
Author-email: 
Dynamic: author
Dynamic: home-page
Dynamic: summary
